{
  "refundOrders": [
    {
      "id": "RO-0001",
      "reason": "Incorrect size big",
      "store_name": "BookNook",
      "store_logo": "https://picsum.photos/200/300",
      "store_url": "https://picsum.photos/",
      "amount": 1936,
      "active": true,
      "decision": null,
      "items": [
        {
          "name": "Bluetooth Speaker",
          "id": "ITEM-012",
          "price": 199.99,
          "quantity": 3
        },
        {
          "name": "Leather Wallet",
          "id": "ITEM-010",
          "price": 45,
          "quantity": 2
        }
      ]
    },
    {
      "id": "RO-0002",
      "reason": "Damaged product",
      "store_name": "TechWorld",
      "store_logo": "https://picsum.photos/200/300",
      "store_url": "https://picsum.photos/",
      "amount": 1936,
      "active": false,
      "decision": null,
      "items": [
        {
          "name": "Hardcover Novel",
          "id": "ITEM-003",
          "price": 22.5,
          "quantity": 5
        }
      ]
    },
    {
      "id": "RO-0003",
      "reason": "Wrong color received",
      "store_name": "BookNook",
      "store_logo": "https://picsum.photos/200/300",
      "store_url": "https://picsum.photos/",
      "amount": 1936,
      "active": false,
      "decision": null,
      "items": [
        {
          "name": "Table Lamp",
          "id": "ITEM-005",
          "price": 34.38,
          "quantity": 1
        },
        {
          "name": "Running Shoes",
          "id": "ITEM-008",
          "price": 79.99,
          "quantity": 10
        }
      ]
    },
    {
      "id": "RO-0004",
      "reason": "Late delivery",
      "store_name": "GadgetStore",
      "store_logo": "https://picsum.photos/200/300",
      "store_url": "https://picsum.photos/",
      "amount": 1936,
      "active": false,
      "decision": null,
      "items": [
        {
          "name": "Running Shoes",
          "id": "ITEM-008",
          "price": 79.99,
          "quantity": 10
        }
      ]
    },
    {
      "id": "RO-0005",
      "reason": "Product not as described",
      "store_name": "HomeEssentials",
      "store_logo": "https://picsum.photos/200/300",
      "store_url": "https://picsum.photos/",
      "amount": 1936,
      "active": true,
      "decision": null,
      "items": [
        {
          "name": "Table Lamp",
          "id": "ITEM-005",
          "price": 34.38,
          "quantity": 1
        },
        {
          "name": "Running Shoes",
          "id": "ITEM-008",
          "price": 79.99,
          "quantity": 10
        }
      ]
    },
    {
      "id": "RO-0006",
      "reason": "Defective item",
      "store_name": "TechWorld",
      "store_logo": "https://picsum.photos/200/300",
      "store_url": "https://picsum.photos/",
      "amount": 1936,
      "active": true,
      "decision": null,
      "items": [
        {
          "name": "Hardcover Novel",
          "id": "ITEM-003",
          "price": 22.5,
          "quantity": 5
        }
      ]
    },
    {
      "id": "RO-0007",
      "reason": "Late delivery",
      "store_name": "HomeEssentials",
      "store_logo": "https://picsum.photos/200/300",
      "store_url": "https://picsum.photos/",
      "amount": 1936,
      "active": true,
      "decision": null,
      "items": [
        {
          "name": "Bluetooth Speaker",
          "id": "ITEM-012",
          "price": 199.99,
          "quantity": 3
        },
        {
          "name": "Leather Wallet",
          "id": "ITEM-010",
          "price": 45,
          "quantity": 2
        }
      ]
    },
    {
      "id": "RO-0008",
      "reason": "Damaged product",
      "store_name": "TechWorld",
      "store_logo": "https://picsum.photos/200/300",
      "store_url": "https://picsum.photos/",
      "amount": 1936,
      "active": false,
      "decision": null,
      "items": [
        {
          "name": "Leather Wallet",
          "id": "ITEM-010",
          "price": 45,
          "quantity": 2
        },
        {
          "name": "Table Lamp",
          "id": "ITEM-005",
          "price": 34.38,
          "quantity": 1
        },
        {
          "name": "Running Shoes",
          "id": "ITEM-008",
          "price": 79.99,
          "quantity": 10
        }
      ]
    },
    {
      "id": "RO-0009",
      "reason": "Wrong item received",
      "store_name": "BookNook",
      "store_logo": "https://picsum.photos/200/300",
      "store_url": "https://picsum.photos/",
      "amount": 1936,
      "active": false,
      "decision": null,
      "items": [
        {
          "name": "Bluetooth Speaker",
          "id": "ITEM-012",
          "price": 199.99,
          "quantity": 3
        },
        {
          "name": "Leather Wallet",
          "id": "ITEM-010",
          "price": 45,
          "quantity": 2
        }
      ]
    },
    {
      "id": "RO-0010",
      "reason": "Defective item",
      "store_name": "FootwearHub",
      "store_logo": "https://picsum.photos/200/300",
      "store_url": "https://picsum.photos/",
      "amount": 1936,
      "active": true,
      "decision": null,
      "items": [
        {
          "name": "Running Shoes",
          "id": "ITEM-008",
          "price": 79.99,
          "quantity": 10
        }
      ]
    },
    {
      "id": "RO-0011",
      "reason": "Defective item",
      "store_name": "FootwearHub",
      "store_logo": "https://picsum.photos/200/300",
      "store_url": "https://picsum.photos/",
      "amount": 1936,
      "active": false,
      "decision": null,
      "items": [
        {
          "name": "Table Lamp",
          "id": "ITEM-005",
          "price": 34.38,
          "quantity": 1
        },
        {
          "name": "Running Shoes",
          "id": "ITEM-008",
          "price": 79.99,
          "quantity": 10
        }
      ]
    },
    {
      "id": "RO-0012",
      "reason": "Product not as described",
      "store_name": "GadgetStore",
      "store_logo": "https://picsum.photos/200/300",
      "store_url": "https://picsum.photos/",
      "amount": 1936,
      "active": true,
      "decision": null,
      "items": [
        {
          "name": "Hardcover Novel",
          "id": "ITEM-003",
          "price": 22.5,
          "quantity": 5
        }
      ]
    },
    {
      "id": "RO-0013",
      "reason": "Product not as described",
      "store_name": "BookNook",
      "store_logo": "https://picsum.photos/200/300",
      "store_url": "https://picsum.photos/",
      "amount": 1936,
      "active": false,
      "decision": null,
      "items": [
        {
          "name": "Bluetooth Speaker",
          "id": "ITEM-012",
          "price": 199.99,
          "quantity": 3
        },
        {
          "name": "Leather Wallet",
          "id": "ITEM-010",
          "price": 45,
          "quantity": 2
        }
      ]
    },
    {
      "id": "RO-0014",
      "reason": "Wrong color received",
      "store_name": "BookNook",
      "store_logo": "https://picsum.photos/200/300",
      "store_url": "https://picsum.photos/",
      "amount": 1936,
      "active": true,
      "decision": null,
      "items": [
        {
          "name": "Bluetooth Speaker",
          "id": "ITEM-012",
          "price": 199.99,
          "quantity": 3
        },
        {
          "name": "Leather Wallet",
          "id": "ITEM-010",
          "price": 45,
          "quantity": 2
        }
      ]
    },
    {
      "id": "RO-0015",
      "reason": "Defective item",
      "store_name": "TechWorld",
      "store_logo": "https://picsum.photos/200/300",
      "store_url": "https://picsum.photos/",
      "amount": 1936,
      "active": false,
      "decision": null,
      "items": [
        {
          "name": "Leather Wallet",
          "id": "ITEM-010",
          "price": 45,
          "quantity": 2
        },
        {
          "name": "Table Lamp",
          "id": "ITEM-005",
          "price": 34.38,
          "quantity": 1
        },
        {
          "name": "Running Shoes",
          "id": "ITEM-008",
          "price": 79.99,
          "quantity": 10
        }
      ]
    },
    {
      "id": "RO-0016",
      "reason": "Wrong item received",
      "store_name": "GadgetStore",
      "store_logo": "https://picsum.photos/200/300",
      "store_url": "https://picsum.photos/",
      "amount": 1936,
      "active": false,
      "decision": null,
      "items": [
        {
          "name": "Running Shoes",
          "id": "ITEM-008",
          "price": 79.99,
          "quantity": 10
        }
      ]
    },
    {
      "id": "RO-0017",
      "reason": "Wrong color received",
      "store_name": "FashionFix",
      "store_logo": "https://picsum.photos/200/300",
      "store_url": "https://picsum.photos/",
      "amount": 1936,
      "active": false,
      "decision": null,
      "items": [
        {
          "name": "Hardcover Novel",
          "id": "ITEM-003",
          "price": 22.5,
          "quantity": 5
        }
      ]
    },
    {
      "id": "RO-0018",
      "reason": "Wrong item received",
      "store_name": "FashionFix",
      "store_logo": "https://picsum.photos/200/300",
      "store_url": "https://picsum.photos/",
      "amount": 1936,
      "active": true,
      "decision": null,
      "items": [
        {
          "name": "Leather Wallet",
          "id": "ITEM-010",
          "price": 45,
          "quantity": 2
        },
        {
          "name": "Table Lamp",
          "id": "ITEM-005",
          "price": 34.38,
          "quantity": 1
        },
        {
          "name": "Running Shoes",
          "id": "ITEM-008",
          "price": 79.99,
          "quantity": 10
        }
      ]
    },
    {
      "id": "RO-0019",
      "reason": "Defective item",
      "store_name": "BookNook",
      "store_logo": "https://picsum.photos/200/300",
      "store_url": "https://picsum.photos/",
      "amount": 1936,
      "active": true,
      "decision": null,
      "items": [
        {
          "name": "Hardcover Novel",
          "id": "ITEM-003",
          "price": 22.5,
          "quantity": 5
        }
      ]
    },
    {
      "id": "RO-0020",
      "reason": "Defective item",
      "store_name": "BookNook",
      "store_logo": "https://picsum.photos/200/300",
      "store_url": "https://picsum.photos/",
      "amount": 1936,
      "active": false,
      "decision": null,
      "items": [
        {
          "name": "Table Lamp",
          "id": "ITEM-005",
          "price": 34.38,
          "quantity": 1
        },
        {
          "name": "Running Shoes",
          "id": "ITEM-008",
          "price": 79.99,
          "quantity": 10
        }
      ]
    },
    {
      "id": "RO-0021",
      "reason": "Product not as described",
      "store_name": "BookNook",
      "store_logo": "https://picsum.photos/200/300",
      "store_url": "https://picsum.photos/",
      "amount": 1936,
      "active": true,
      "decision": null,
      "items": [
        {
          "name": "Bluetooth Speaker",
          "id": "ITEM-012",
          "price": 199.99,
          "quantity": 3
        },
        {
          "name": "Leather Wallet",
          "id": "ITEM-010",
          "price": 45,
          "quantity": 2
        }
      ]
    },
    {
      "id": "RO-0022",
      "reason": "Late delivery",
      "store_name": "TechWorld",
      "store_logo": "https://picsum.photos/200/300",
      "store_url": "https://picsum.photos/",
      "amount": 1936,
      "active": false,
      "decision": null,
      "items": [
        {
          "name": "Running Shoes",
          "id": "ITEM-008",
          "price": 79.99,
          "quantity": 10
        }
      ]
    },
    {
      "id": "RO-0023",
      "reason": "Wrong item received",
      "store_name": "BookNook",
      "store_logo": "https://picsum.photos/200/300",
      "store_url": "https://picsum.photos/",
      "amount": 1936,
      "active": false,
      "decision": null,
      "items": [
        {
          "name": "Hardcover Novel",
          "id": "ITEM-003",
          "price": 22.5,
          "quantity": 5
        }
      ]
    },
    {
      "id": "RO-0024",
      "reason": "Wrong item received",
      "store_name": "BookNook",
      "store_logo": "https://picsum.photos/200/300",
      "store_url": "https://picsum.photos/",
      "amount": 1936,
      "active": false,
      "decision": null,
      "items": [
        {
          "name": "Leather Wallet",
          "id": "ITEM-010",
          "price": 45,
          "quantity": 2
        },
        {
          "name": "Table Lamp",
          "id": "ITEM-005",
          "price": 34.38,
          "quantity": 1
        },
        {
          "name": "Running Shoes",
          "id": "ITEM-008",
          "price": 79.99,
          "quantity": 10
        }
      ]
    },
    {
      "id": "RO-0025",
      "reason": "Damaged product",
      "store_name": "TechWorld",
      "store_logo": "https://picsum.photos/200/300",
      "store_url": "https://picsum.photos/",
      "amount": 1936,
      "active": true,
      "decision": null,
      "items": [
        {
          "name": "Bluetooth Speaker",
          "id": "ITEM-012",
          "price": 199.99,
          "quantity": 3
        },
        {
          "name": "Leather Wallet",
          "id": "ITEM-010",
          "price": 45,
          "quantity": 2
        }
      ]
    },
    {
      "id": "RO-0026",
      "reason": "Incorrect size",
      "store_name": "BookNook",
      "store_logo": "https://picsum.photos/200/300",
      "store_url": "https://picsum.photos/",
      "amount": 1936,
      "active": false,
      "decision": null,
      "items": [
        {
          "name": "Table Lamp",
          "id": "ITEM-005",
          "price": 34.38,
          "quantity": 1
        },
        {
          "name": "Running Shoes",
          "id": "ITEM-008",
          "price": 79.99,
          "quantity": 10
        }
      ]
    },
    {
      "id": "RO-0027",
      "reason": "Damaged product",
      "store_name": "FootwearHub",
      "store_logo": "https://picsum.photos/200/300",
      "store_url": "https://picsum.photos/",
      "amount": 1936,
      "active": true,
      "decision": null,
      "items": [
        {
          "name": "Hardcover Novel",
          "id": "ITEM-003",
          "price": 22.5,
          "quantity": 5
        }
      ]
    },
    {
      "id": "RO-0028",
      "reason": "Wrong color received",
      "store_name": "FashionFix",
      "store_logo": "https://picsum.photos/200/300",
      "store_url": "https://picsum.photos/",
      "amount": 1936,
      "active": true,
      "decision": null,
      "items": [
        {
          "name": "Hardcover Novel",
          "id": "ITEM-003",
          "price": 22.5,
          "quantity": 5
        }
      ]
    },
    {
      "id": "RO-0029",
      "reason": "Defective item",
      "store_name": "HomeEssentials",
      "store_logo": "https://picsum.photos/200/300",
      "store_url": "https://picsum.photos/",
      "amount": 1936,
      "active": true,
      "decision": null,
      "items": [
        {
          "name": "Table Lamp",
          "id": "ITEM-005",
          "price": 34.38,
          "quantity": 1
        },
        {
          "name": "Running Shoes",
          "id": "ITEM-008",
          "price": 79.99,
          "quantity": 10
        }
      ]
    },
    {
      "id": "RO-0030",
      "reason": "Defective item",
      "store_name": "GadgetStore",
      "store_logo": "https://picsum.photos/200/300",
      "store_url": "https://picsum.photos/",
      "amount": 1936,
      "active": false,
      "decision": null,
      "items": [
        {
          "name": "Table Lamp",
          "id": "ITEM-005",
          "price": 34.38,
          "quantity": 1
        },
        {
          "name": "Running Shoes",
          "id": "ITEM-008",
          "price": 79.99,
          "quantity": 10
        }
      ]
    },
    {
      "id": "RO-0031",
      "reason": "Late delivery",
      "store_name": "GadgetStore",
      "store_logo": "https://picsum.photos/200/300",
      "store_url": "https://picsum.photos/",
      "amount": 1936,
      "active": false,
      "decision": null,
      "items": [
        {
          "name": "Running Shoes",
          "id": "ITEM-008",
          "price": 79.99,
          "quantity": 10
        }
      ]
    },
    {
      "id": "RO-0032",
      "reason": "Wrong item received",
      "store_name": "HomeEssentials",
      "store_logo": "https://picsum.photos/200/300",
      "store_url": "https://picsum.photos/",
      "amount": 1936,
      "active": true,
      "decision": null,
      "items": [
        {
          "name": "Bluetooth Speaker",
          "id": "ITEM-012",
          "price": 199.99,
          "quantity": 3
        },
        {
          "name": "Leather Wallet",
          "id": "ITEM-010",
          "price": 45,
          "quantity": 2
        }
      ]
    },
    {
      "id": "RO-0033",
      "reason": "Defective item",
      "store_name": "FootwearHub",
      "store_logo": "https://picsum.photos/200/300",
      "store_url": "https://picsum.photos/",
      "amount": 1936,
      "active": false,
      "decision": null,
      "items": [
        {
          "name": "Bluetooth Speaker",
          "id": "ITEM-012",
          "price": 199.99,
          "quantity": 3
        },
        {
          "name": "Leather Wallet",
          "id": "ITEM-010",
          "price": 45,
          "quantity": 2
        }
      ]
    },
    {
      "id": "RO-0034",
      "reason": "Damaged product",
      "store_name": "GadgetStore",
      "store_logo": "https://picsum.photos/200/300",
      "store_url": "https://picsum.photos/",
      "amount": 1936,
      "active": false,
      "decision": null,
      "items": [
        {
          "name": "Leather Wallet",
          "id": "ITEM-010",
          "price": 45,
          "quantity": 2
        },
        {
          "name": "Table Lamp",
          "id": "ITEM-005",
          "price": 34.38,
          "quantity": 1
        },
        {
          "name": "Running Shoes",
          "id": "ITEM-008",
          "price": 79.99,
          "quantity": 10
        }
      ]
    },
    {
      "id": "RO-0035",
      "reason": "Defective item",
      "store_name": "HomeEssentials",
      "store_logo": "https://picsum.photos/200/300",
      "store_url": "https://picsum.photos/",
      "amount": 1936,
      "active": false,
      "decision": null,
      "items": [
        {
          "name": "Leather Wallet",
          "id": "ITEM-010",
          "price": 45,
          "quantity": 2
        },
        {
          "name": "Table Lamp",
          "id": "ITEM-005",
          "price": 34.38,
          "quantity": 1
        },
        {
          "name": "Running Shoes",
          "id": "ITEM-008",
          "price": 79.99,
          "quantity": 10
        }
      ]
    },
    {
      "id": "RO-0036",
      "reason": "Wrong item received",
      "store_name": "FashionFix",
      "store_logo": "https://picsum.photos/200/300",
      "store_url": "https://picsum.photos/",
      "amount": 1936,
      "active": true,
      "decision": null,
      "items": [
        {
          "name": "Running Shoes",
          "id": "ITEM-008",
          "price": 79.99,
          "quantity": 10
        }
      ]
    },
    {
      "id": "RO-0037",
      "reason": "Defective item",
      "store_name": "GadgetStore",
      "store_logo": "https://picsum.photos/200/300",
      "store_url": "https://picsum.photos/",
      "amount": 1936,
      "active": false,
      "decision": null,
      "items": [
        {
          "name": "Bluetooth Speaker",
          "id": "ITEM-012",
          "price": 199.99,
          "quantity": 3
        },
        {
          "name": "Leather Wallet",
          "id": "ITEM-010",
          "price": 45,
          "quantity": 2
        }
      ]
    },
    {
      "id": "RO-0038",
      "reason": "Product not as described",
      "store_name": "FashionFix",
      "store_logo": "https://picsum.photos/200/300",
      "store_url": "https://picsum.photos/",
      "amount": 1936,
      "active": false,
      "decision": null,
      "items": [
        {
          "name": "Hardcover Novel",
          "id": "ITEM-003",
          "price": 22.5,
          "quantity": 5
        }
      ]
    },
    {
      "id": "RO-0039",
      "reason": "Defective item",
      "store_name": "HomeEssentials",
      "store_logo": "https://picsum.photos/200/300",
      "store_url": "https://picsum.photos/",
      "amount": 1936,
      "active": true,
      "decision": null,
      "items": [
        {
          "name": "Leather Wallet",
          "id": "ITEM-010",
          "price": 45,
          "quantity": 2
        },
        {
          "name": "Table Lamp",
          "id": "ITEM-005",
          "price": 34.38,
          "quantity": 1
        },
        {
          "name": "Running Shoes",
          "id": "ITEM-008",
          "price": 79.99,
          "quantity": 10
        }
      ]
    },
    {
      "id": "RO-0040",
      "reason": "Late delivery",
      "store_name": "TechWorld",
      "store_logo": "https://picsum.photos/200/300",
      "store_url": "https://picsum.photos/",
      "amount": 1936,
      "active": true,
      "decision": null,
      "items": [
        {
          "name": "Bluetooth Speaker",
          "id": "ITEM-012",
          "price": 199.99,
          "quantity": 3
        },
        {
          "name": "Leather Wallet",
          "id": "ITEM-010",
          "price": 45,
          "quantity": 2
        }
      ]
    },
    {
      "id": "RO-0041",
      "reason": "Damaged product",
      "store_name": "FootwearHub",
      "store_logo": "https://picsum.photos/200/300",
      "store_url": "https://picsum.photos/",
      "amount": 1936,
      "active": true,
      "decision": null,
      "items": [
        {
          "name": "Leather Wallet",
          "id": "ITEM-010",
          "price": 45,
          "quantity": 2
        },
        {
          "name": "Table Lamp",
          "id": "ITEM-005",
          "price": 34.38,
          "quantity": 1
        },
        {
          "name": "Running Shoes",
          "id": "ITEM-008",
          "price": 79.99,
          "quantity": 10
        }
      ]
    },
    {
      "id": "RO-0042",
      "reason": "Product not as described",
      "store_name": "HomeEssentials",
      "store_logo": "https://picsum.photos/200/300",
      "store_url": "https://picsum.photos/",
      "amount": 1936,
      "active": true,
      "decision": null,
      "items": [
        {
          "name": "Running Shoes",
          "id": "ITEM-008",
          "price": 79.99,
          "quantity": 10
        }
      ]
    },
    {
      "id": "RO-0043",
      "reason": "Damaged product",
      "store_name": "FashionFix",
      "store_logo": "https://picsum.photos/200/300",
      "store_url": "https://picsum.photos/",
      "amount": 1936,
      "active": true,
      "decision": null,
      "items": [
        {
          "name": "Table Lamp",
          "id": "ITEM-005",
          "price": 34.38,
          "quantity": 1
        },
        {
          "name": "Running Shoes",
          "id": "ITEM-008",
          "price": 79.99,
          "quantity": 10
        }
      ]
    },
    {
      "id": "RO-0044",
      "reason": "Defective item",
      "store_name": "FootwearHub",
      "store_logo": "https://picsum.photos/200/300",
      "store_url": "https://picsum.photos/",
      "amount": 1936,
      "active": true,
      "decision": null,
      "items": [
        {
          "name": "Leather Wallet",
          "id": "ITEM-010",
          "price": 45,
          "quantity": 2
        },
        {
          "name": "Table Lamp",
          "id": "ITEM-005",
          "price": 34.38,
          "quantity": 1
        },
        {
          "name": "Running Shoes",
          "id": "ITEM-008",
          "price": 79.99,
          "quantity": 10
        }
      ]
    },
    {
      "id": "RO-0045",
      "reason": "Wrong color received",
      "store_name": "FootwearHub",
      "store_logo": "https://picsum.photos/200/300",
      "store_url": "https://picsum.photos/",
      "amount": 1936,
      "active": true,
      "decision": null,
      "items": [
        {
          "name": "Bluetooth Speaker",
          "id": "ITEM-012",
          "price": 199.99,
          "quantity": 3
        },
        {
          "name": "Leather Wallet",
          "id": "ITEM-010",
          "price": 45,
          "quantity": 2
        }
      ]
    },
    {
      "id": "RO-0046",
      "reason": "Wrong item received",
      "store_name": "FashionFix",
      "store_logo": "https://picsum.photos/200/300",
      "store_url": "https://picsum.photos/",
      "amount": 1936,
      "active": false,
      "decision": null,
      "items": [
        {
          "name": "Running Shoes",
          "id": "ITEM-008",
          "price": 79.99,
          "quantity": 10
        }
      ]
    },
    {
      "id": "RO-0047",
      "reason": "Incorrect size",
      "store_name": "HomeEssentials",
      "store_logo": "https://picsum.photos/200/300",
      "store_url": "https://picsum.photos/",
      "amount": 1936,
      "active": true,
      "decision": null,
      "items": [
        {
          "name": "Table Lamp",
          "id": "ITEM-005",
          "price": 34.38,
          "quantity": 1
        },
        {
          "name": "Running Shoes",
          "id": "ITEM-008",
          "price": 79.99,
          "quantity": 10
        }
      ]
    },
    {
      "id": "RO-0048",
      "reason": "Wrong item received",
      "store_name": "FashionFix",
      "store_logo": "https://picsum.photos/200/300",
      "store_url": "https://picsum.photos/",
      "amount": 1936,
      "active": true,
      "decision": null,
      "items": [
        {
          "name": "Table Lamp",
          "id": "ITEM-005",
          "price": 34.38,
          "quantity": 1
        },
        {
          "name": "Running Shoes",
          "id": "ITEM-008",
          "price": 79.99,
          "quantity": 10
        }
      ]
    },
    {
      "id": "RO-0049",
      "reason": "Damaged product",
      "store_name": "BookNook",
      "store_logo": "https://picsum.photos/200/300",
      "store_url": "https://picsum.photos/",
      "amount": 1936,
      "active": false,
      "decision": null,
      "items": [
        {
          "name": "Running Shoes",
          "id": "ITEM-008",
          "price": 79.99,
          "quantity": 10
        }
      ]
    },
    {
      "id": "RO-0050",
      "reason": "Defective item",
      "store_name": "BookNook",
      "store_logo": "https://picsum.photos/200/300",
      "store_url": "https://picsum.photos/",
      "amount": 1936,
      "active": true,
      "decision": null,
      "items": [
        {
          "name": "Bluetooth Speaker",
          "id": "ITEM-012",
          "price": 199.99,
          "quantity": 3
        },
        {
          "name": "Leather Wallet",
          "id": "ITEM-010",
          "price": 45,
          "quantity": 2
        }
      ]
    },
    {
      "id": "RO-0051",
      "reason": "Late delivery",
      "store_name": "BookNook",
      "store_logo": "https://picsum.photos/200/300",
      "store_url": "https://picsum.photos/",
      "amount": 1936,
      "active": false,
      "decision": null,
      "items": [
        {
          "name": "Hardcover Novel",
          "id": "ITEM-003",
          "price": 22.5,
          "quantity": 5
        }
      ]
    },
    {
      "id": "RO-0052",
      "reason": "Late delivery",
      "store_name": "GadgetStore",
      "store_logo": "https://picsum.photos/200/300",
      "store_url": "https://picsum.photos/",
      "amount": 1936,
      "active": false,
      "decision": null,
      "items": [
        {
          "name": "Hardcover Novel",
          "id": "ITEM-003",
          "price": 22.5,
          "quantity": 5
        }
      ]
    },
    {
      "id": "RO-0053",
      "reason": "Wrong item received",
      "store_name": "GadgetStore",
      "store_logo": "https://picsum.photos/200/300",
      "store_url": "https://picsum.photos/",
      "amount": 1936,
      "active": true,
      "decision": null,
      "items": [
        {
          "name": "Leather Wallet",
          "id": "ITEM-010",
          "price": 45,
          "quantity": 2
        },
        {
          "name": "Table Lamp",
          "id": "ITEM-005",
          "price": 34.38,
          "quantity": 1
        },
        {
          "name": "Running Shoes",
          "id": "ITEM-008",
          "price": 79.99,
          "quantity": 10
        }
      ]
    },
    {
      "id": "RO-0054",
      "reason": "Damaged product",
      "store_name": "HomeEssentials",
      "store_logo": "https://picsum.photos/200/300",
      "store_url": "https://picsum.photos/",
      "amount": 1936,
      "active": false,
      "decision": null,
      "items": [
        {
          "name": "Table Lamp",
          "id": "ITEM-005",
          "price": 34.38,
          "quantity": 1
        },
        {
          "name": "Running Shoes",
          "id": "ITEM-008",
          "price": 79.99,
          "quantity": 10
        }
      ]
    },
    {
      "id": "RO-0055",
      "reason": "Damaged product",
      "store_name": "TechWorld",
      "store_logo": "https://picsum.photos/200/300",
      "store_url": "https://picsum.photos/",
      "amount": 1936,
      "active": false,
      "decision": null,
      "items": [
        {
          "name": "Leather Wallet",
          "id": "ITEM-010",
          "price": 45,
          "quantity": 2
        },
        {
          "name": "Table Lamp",
          "id": "ITEM-005",
          "price": 34.38,
          "quantity": 1
        },
        {
          "name": "Running Shoes",
          "id": "ITEM-008",
          "price": 79.99,
          "quantity": 10
        }
      ]
    },
    {
      "id": "RO-0056",
      "reason": "Wrong item received",
      "store_name": "HomeEssentials",
      "store_logo": "https://picsum.photos/200/300",
      "store_url": "https://picsum.photos/",
      "amount": 1936,
      "active": false,
      "decision": null,
      "items": [
        {
          "name": "Table Lamp",
          "id": "ITEM-005",
          "price": 34.38,
          "quantity": 1
        },
        {
          "name": "Running Shoes",
          "id": "ITEM-008",
          "price": 79.99,
          "quantity": 10
        }
      ]
    },
    {
      "id": "RO-0057",
      "reason": "Incorrect size",
      "store_name": "FootwearHub",
      "store_logo": "https://picsum.photos/200/300",
      "store_url": "https://picsum.photos/",
      "amount": 1936,
      "active": false,
      "decision": null,
      "items": [
        {
          "name": "Leather Wallet",
          "id": "ITEM-010",
          "price": 45,
          "quantity": 2
        },
        {
          "name": "Table Lamp",
          "id": "ITEM-005",
          "price": 34.38,
          "quantity": 1
        },
        {
          "name": "Running Shoes",
          "id": "ITEM-008",
          "price": 79.99,
          "quantity": 10
        }
      ]
    },
    {
      "id": "RO-0058",
      "reason": "Wrong color received",
      "store_name": "FootwearHub",
      "store_logo": "https://picsum.photos/200/300",
      "store_url": "https://picsum.photos/",
      "amount": 1936,
      "active": true,
      "decision": null,
      "items": [
        {
          "name": "Leather Wallet",
          "id": "ITEM-010",
          "price": 45,
          "quantity": 2
        },
        {
          "name": "Table Lamp",
          "id": "ITEM-005",
          "price": 34.38,
          "quantity": 1
        },
        {
          "name": "Running Shoes",
          "id": "ITEM-008",
          "price": 79.99,
          "quantity": 10
        }
      ]
    },
    {
      "id": "RO-0059",
      "reason": "Product not as described",
      "store_name": "BookNook",
      "store_logo": "https://picsum.photos/200/300",
      "store_url": "https://picsum.photos/",
      "amount": 1936,
      "active": true,
      "decision": null,
      "items": [
        {
          "name": "Bluetooth Speaker",
          "id": "ITEM-012",
          "price": 199.99,
          "quantity": 3
        },
        {
          "name": "Leather Wallet",
          "id": "ITEM-010",
          "price": 45,
          "quantity": 2
        }
      ]
    },
    {
      "id": "RO-0060",
      "reason": "Wrong color received",
      "store_name": "FootwearHub",
      "store_logo": "https://picsum.photos/200/300",
      "store_url": "https://picsum.photos/",
      "amount": 1936,
      "active": true,
      "decision": null,
      "items": [
        {
          "name": "Leather Wallet",
          "id": "ITEM-010",
          "price": 45,
          "quantity": 2
        },
        {
          "name": "Table Lamp",
          "id": "ITEM-005",
          "price": 34.38,
          "quantity": 1
        },
        {
          "name": "Running Shoes",
          "id": "ITEM-008",
          "price": 79.99,
          "quantity": 10
        }
      ]
    },
    {
      "id": "RO-0061",
      "reason": "Late delivery",
      "store_name": "GadgetStore",
      "store_logo": "https://picsum.photos/200/300",
      "store_url": "https://picsum.photos/",
      "amount": 1936,
      "active": true,
      "decision": null,
      "items": [
        {
          "name": "Running Shoes",
          "id": "ITEM-008",
          "price": 79.99,
          "quantity": 10
        }
      ]
    },
    {
      "id": "RO-0062",
      "reason": "Wrong item received",
      "store_name": "TechWorld",
      "store_logo": "https://picsum.photos/200/300",
      "store_url": "https://picsum.photos/",
      "amount": 1936,
      "active": false,
      "decision": null,
      "items": [
        {
          "name": "Table Lamp",
          "id": "ITEM-005",
          "price": 34.38,
          "quantity": 1
        },
        {
          "name": "Running Shoes",
          "id": "ITEM-008",
          "price": 79.99,
          "quantity": 10
        }
      ]
    },
    {
      "id": "RO-0063",
      "reason": "Damaged product",
      "store_name": "TechWorld",
      "store_logo": "https://picsum.photos/200/300",
      "store_url": "https://picsum.photos/",
      "amount": 1936,
      "active": false,
      "decision": null,
      "items": [
        {
          "name": "Leather Wallet",
          "id": "ITEM-010",
          "price": 45,
          "quantity": 2
        },
        {
          "name": "Table Lamp",
          "id": "ITEM-005",
          "price": 34.38,
          "quantity": 1
        },
        {
          "name": "Running Shoes",
          "id": "ITEM-008",
          "price": 79.99,
          "quantity": 10
        }
      ]
    },
    {
      "id": "RO-0064",
      "reason": "Incorrect size",
      "store_name": "TechWorld",
      "store_logo": "https://picsum.photos/200/300",
      "store_url": "https://picsum.photos/",
      "amount": 1936,
      "active": true,
      "decision": null,
      "items": [
        {
          "name": "Table Lamp",
          "id": "ITEM-005",
          "price": 34.38,
          "quantity": 1
        },
        {
          "name": "Running Shoes",
          "id": "ITEM-008",
          "price": 79.99,
          "quantity": 10
        }
      ]
    },
    {
      "id": "RO-0065",
      "reason": "Incorrect size",
      "store_name": "TechWorld",
      "store_logo": "https://picsum.photos/200/300",
      "store_url": "https://picsum.photos/",
      "amount": 1936,
      "active": true,
      "decision": null,
      "items": [
        {
          "name": "Table Lamp",
          "id": "ITEM-005",
          "price": 34.38,
          "quantity": 1
        },
        {
          "name": "Running Shoes",
          "id": "ITEM-008",
          "price": 79.99,
          "quantity": 10
        }
      ]
    },
    {
      "id": "RO-0066",
      "reason": "Wrong item received",
      "store_name": "HomeEssentials",
      "store_logo": "https://picsum.photos/200/300",
      "store_url": "https://picsum.photos/",
      "amount": 1936,
      "active": false,
      "decision": null,
      "items": [
        {
          "name": "Leather Wallet",
          "id": "ITEM-010",
          "price": 45,
          "quantity": 2
        },
        {
          "name": "Table Lamp",
          "id": "ITEM-005",
          "price": 34.38,
          "quantity": 1
        },
        {
          "name": "Running Shoes",
          "id": "ITEM-008",
          "price": 79.99,
          "quantity": 10
        }
      ]
    },
    {
      "id": "RO-0067",
      "reason": "Incorrect size",
      "store_name": "TechWorld",
      "store_logo": "https://picsum.photos/200/300",
      "store_url": "https://picsum.photos/",
      "amount": 1936,
      "active": true,
      "decision": null,
      "items": [
        {
          "name": "Bluetooth Speaker",
          "id": "ITEM-012",
          "price": 199.99,
          "quantity": 3
        },
        {
          "name": "Leather Wallet",
          "id": "ITEM-010",
          "price": 45,
          "quantity": 2
        }
      ]
    },
    {
      "id": "RO-0068",
      "reason": "Wrong item received",
      "store_name": "TechWorld",
      "store_logo": "https://picsum.photos/200/300",
      "store_url": "https://picsum.photos/",
      "amount": 1936,
      "active": false,
      "decision": null,
      "items": [
        {
          "name": "Table Lamp",
          "id": "ITEM-005",
          "price": 34.38,
          "quantity": 1
        },
        {
          "name": "Running Shoes",
          "id": "ITEM-008",
          "price": 79.99,
          "quantity": 10
        }
      ]
    },
    {
      "id": "RO-0069",
      "reason": "Product not as described",
      "store_name": "GadgetStore",
      "store_logo": "https://picsum.photos/200/300",
      "store_url": "https://picsum.photos/",
      "amount": 1936,
      "active": true,
      "decision": null,
      "items": [
        {
          "name": "Bluetooth Speaker",
          "id": "ITEM-012",
          "price": 199.99,
          "quantity": 3
        },
        {
          "name": "Leather Wallet",
          "id": "ITEM-010",
          "price": 45,
          "quantity": 2
        }
      ]
    },
    {
      "id": "RO-0070",
      "reason": "Wrong item received",
      "store_name": "FashionFix",
      "store_logo": "https://picsum.photos/200/300",
      "store_url": "https://picsum.photos/",
      "amount": 1936,
      "active": false,
      "decision": null,
      "items": [
        {
          "name": "Bluetooth Speaker",
          "id": "ITEM-012",
          "price": 199.99,
          "quantity": 3
        },
        {
          "name": "Leather Wallet",
          "id": "ITEM-010",
          "price": 45,
          "quantity": 2
        }
      ]
    },
    {
      "id": "RO-0071",
      "reason": "Product not as described",
      "store_name": "FashionFix",
      "store_logo": "https://picsum.photos/200/300",
      "store_url": "https://picsum.photos/",
      "amount": 1936,
      "active": true,
      "decision": null,
      "items": [
        {
          "name": "Running Shoes",
          "id": "ITEM-008",
          "price": 79.99,
          "quantity": 10
        }
      ]
    },
    {
      "id": "RO-0072",
      "reason": "Damaged product",
      "store_name": "FootwearHub",
      "store_logo": "https://picsum.photos/200/300",
      "store_url": "https://picsum.photos/",
      "amount": 1936,
      "active": true,
      "decision": null,
      "items": [
        {
          "name": "Leather Wallet",
          "id": "ITEM-010",
          "price": 45,
          "quantity": 2
        },
        {
          "name": "Table Lamp",
          "id": "ITEM-005",
          "price": 34.38,
          "quantity": 1
        },
        {
          "name": "Running Shoes",
          "id": "ITEM-008",
          "price": 79.99,
          "quantity": 10
        }
      ]
    },
    {
      "id": "RO-0073",
      "reason": "Incorrect size",
      "store_name": "TechWorld",
      "store_logo": "https://picsum.photos/200/300",
      "store_url": "https://picsum.photos/",
      "amount": 1936,
      "active": false,
      "decision": null,
      "items": [
        {
          "name": "Table Lamp",
          "id": "ITEM-005",
          "price": 34.38,
          "quantity": 1
        },
        {
          "name": "Running Shoes",
          "id": "ITEM-008",
          "price": 79.99,
          "quantity": 10
        }
      ]
    }
  ]
}